lightwood/__about__.py
lightwood/__init__.py
lightwood/analysis/__init__.py
lightwood/analysis/analyze.py
lightwood/analysis/base.py
lightwood/analysis/explain.py
lightwood/analysis/helpers/__init__.py
lightwood/analysis/helpers/acc_stats.py
lightwood/analysis/helpers/conf_stats.py
lightwood/analysis/helpers/feature_importance.py
lightwood/analysis/helpers/pyod.py
lightwood/analysis/helpers/shap.py
lightwood/analysis/nc/LICENSE
lightwood/analysis/nc/__init__.py
lightwood/analysis/nc/base.py
lightwood/analysis/nc/calibrate.py
lightwood/analysis/nc/icp.py
lightwood/analysis/nc/metrics.py
lightwood/analysis/nc/nc.py
lightwood/analysis/nc/norm.py
lightwood/analysis/nc/util.py
lightwood/analysis/nn_conf/__init__.py
lightwood/analysis/nn_conf/temp_scale.py
lightwood/analysis/nn_conf/temp_scale_license
lightwood/api/__init__.py
lightwood/api/high_level.py
lightwood/api/json_ai.py
lightwood/api/predictor.py
lightwood/api/types.py
lightwood/data/__init__.py
lightwood/data/encoded_ds.py
lightwood/data/timeseries_analyzer.py
lightwood/data/timeseries_transform.py
lightwood/encoder/__init__.py
lightwood/encoder/array/__init__.py
lightwood/encoder/array/array.py
lightwood/encoder/array/ts_cat_array.py
lightwood/encoder/array/ts_num_array.py
lightwood/encoder/audio/__init__.py
lightwood/encoder/audio/mfcc.py
lightwood/encoder/base.py
lightwood/encoder/categorical/__init__.py
lightwood/encoder/categorical/autoencoder.py
lightwood/encoder/categorical/binary.py
lightwood/encoder/categorical/gym.py
lightwood/encoder/categorical/multihot.py
lightwood/encoder/categorical/onehot.py
lightwood/encoder/categorical/simple_label.py
lightwood/encoder/datetime/__init__.py
lightwood/encoder/datetime/datetime.py
lightwood/encoder/datetime/datetime_sin_normalizer.py
lightwood/encoder/helpers.py
lightwood/encoder/identity/__init__.py
lightwood/encoder/identity/identity.py
lightwood/encoder/image/__init__.py
lightwood/encoder/image/helpers/__init__.py
lightwood/encoder/image/helpers/img_to_vec.py
lightwood-25.9.1.0.dist-info/LICENSE
lightwood-25.9.1.0.dist-info/METADATA
lightwood-25.9.1.0.dist-info/WHEEL
lightwood-25.9.1.0.dist-info/RECORD
