Metadata-Version: 2.3
Name: lightwood
Version: 25.9.1.0
Summary: Lightwood is Legos for Machine Learning.
License: GPL-3.0-only
Author: MindsDB Inc.
Requires-Python: >=3.10,<3.14
Classifier: License :: OSI Approved :: GNU General Public License v3 (GPLv3)
Classifier: Programming Language :: Python :: 3
Classifier: Programming Language :: Python :: 3.10
Classifier: Programming Language :: Python :: 3.11
Classifier: Programming Language :: Python :: 3.12
Classifier: Programming Language :: Python :: 3.13
Provides-Extra: audio
Provides-Extra: dev
Provides-Extra: extra
Provides-Extra: extra-ts
Provides-Extra: image
Provides-Extra: quantum
Provides-Extra: xai
Requires-Dist: autopep8 (>=1.5.7) ; extra == "dev"
Requires-Dist: black (==24.3.0)
Requires-Dist: colorlog (==6.5.0)
Requires-Dist: dataclasses_json (>=0.5.4)
Requires-Dist: dataprep_ml (==0.0.25)
Requires-Dist: dill (==0.3.6)
Requires-Dist: flake8 (>=6.0.0) ; extra == "dev"
Requires-Dist: gluonts (>=0.13.2,<0.14.0) ; extra == "extra-ts"
Requires-Dist: librosa (==0.8.1) ; extra == "audio"
Requires-Dist: lightgbm (>=4.6.0,<4.7.0) ; extra == "extra"
Requires-Dist: mindsdb-evaluator (==0.0.20)
Requires-Dist: mxnet (>=1.6.0,<2.0.0) ; extra == "extra-ts"
Requires-Dist: neuralforecast (>=1.6.4,<1.7.0) ; extra == "extra-ts"
Requires-Dist: nltk (>=3.9)
Requires-Dist: numpy (>1.23.0)
Requires-Dist: optuna (>=3.6.2,<4.0.0)
Requires-Dist: optuna-integration (>=3.6.0,<4.0.0)
Requires-Dist: pandas (==2.2.3)
Requires-Dist: pillow (>=10.3.0) ; extra == "image"
Requires-Dist: prophet (==1.1) ; extra == "extra-ts"
Requires-Dist: psutil (>=7.0,<8.0)
Requires-Dist: pyod (==1.0.4) ; extra == "xai"
Requires-Dist: pystan (==2.19.1.1) ; extra == "extra-ts"
Requires-Dist: qiskit (==1.4.2) ; extra == "quantum"
Requires-Dist: requests (==2.32.4)
Requires-Dist: scikit-learn (==1.5.2)
Requires-Dist: scipy (>=1.5.4)
Requires-Dist: shap (>=0.40.0) ; extra == "xai"
Requires-Dist: sktime (==0.34.0)
Requires-Dist: statsforecast (>=1.6.0,<1.7.0)
Requires-Dist: suod (>=0.1.3) ; extra == "xai"
Requires-Dist: tab-transformer-pytorch (>=0.2.1)
Requires-Dist: torch (>=2.8.0,<2.9.0)
Requires-Dist: torch_optimizer (==0.1.0)
Requires-Dist: torchvision (>=0.15.0) ; extra == "image"
Requires-Dist: transformers (>=4.48.0)
Requires-Dist: type_infer (==0.0.25)
Requires-Dist: typing_extensions (>=4.8.0)
Requires-Dist: xgboost (>=1.6.0,<=1.8.0)
